Tools/download_results.py
Tools/length_analysis.py
Tools/radar_chart.py
Tools/score_monitor.py
WebUI/app.py
WebUI/layouts.py
WebUI/benchmarks/constant.py
WebUI/benchmarks/page_utils.py
WebUI/benchmarks/pages.py
WebUI/static/LOOM.png
WebUI/utils/device.py
WebUI/utils/evaluate.py
WebUI/utils/rag.py
WebUI/utils/status.py
WebUI/utils/themes.py
WebUI/utils/triggers.py
assets/LOOM-Scope-logo.png
assets/demo.gif
assets/newplot.png
assets/sunburst_plot.png
assets/task-category.png
assets/leaderboard/full_ability_radar_chart.png
benchmarks/README.md
benchmarks/README_ZH.md
benchmarks/__init__.py
benchmarks/Faithfulness/L_CiteEval/L_CiteEval.py
benchmarks/Faithfulness/L_CiteEval/README.md
benchmarks/Faithfulness/L_CiteEval/utils/evaluation/eval_citation.py
benchmarks/Faithfulness/L_CiteEval/utils/evaluation/eval_citation2.py
benchmarks/Faithfulness/L_CiteEval/utils/evaluation/eval_correct.py
benchmarks/Faithfulness/L_CiteEval/utils/evaluation/eval_correct2.py
benchmarks/General/BAMBOO/BAMBOO.py
benchmarks/General/BAMBOO/README.md
benchmarks/General/BAMBOO/utils/evaluation/matrics.py
benchmarks/General/BAMBOO/utils/evaluation/private_eval/data.py
benchmarks/General/BAMBOO/utils/evaluation/private_eval/evaluation.py
benchmarks/General/BAMBOO/utils/evaluation/private_eval/execution.py
benchmarks/General/LEval/LEval.py
benchmarks/General/LEval/README.md
benchmarks/General/LEval/utils/LEval_config.py
benchmarks/General/LEval/utils/process.py
benchmarks/General/LEval/utils/evaluation/LEval_config.py
benchmarks/General/LEval/utils/evaluation/auto_eval.py
benchmarks/General/LEval/utils/evaluation/em.py
benchmarks/General/LEval/utils/evaluation/f1.py
benchmarks/General/LEval/utils/evaluation/rouge.py
benchmarks/General/LongBench/LongBench.py
benchmarks/General/LongBench/README.md
benchmarks/General/LongBench/utils/evaluation/__init__.py
benchmarks/General/LongBench/utils/evaluation/eval.py
benchmarks/General/LongBench/utils/evaluation/metric_name.py
loom_scope-0.8.dist-info/licenses/LICENSE.txt
loom_scope-0.8.dist-info/METADATA
loom_scope-0.8.dist-info/WHEEL
loom_scope-0.8.dist-info/entry_points.txt
loom_scope-0.8.dist-info/top_level.txt
loom_scope-0.8.dist-info/RECORD
