Metadata-Version: 2.4
Name: loom-scope
Version: 0.8
Summary: A Plug-and-Play and Comprehensive evaluation framework specifically for long-context models
Requires-Python: >=3.10
License-File: LICENSE.txt
Requires-Dist: ipdb
Requires-Dist: autopep8
Requires-Dist: docformatter
Requires-Dist: scikit-learn
Requires-Dist: modelscope
Requires-Dist: rank_bm25
Requires-Dist: hf_xet
Requires-Dist: gradio
Requires-Dist: torch==2.6
Requires-Dist: loguru
Requires-Dist: peft
Requires-Dist: openpyxl
Requires-Dist: bert_score
Requires-Dist: nltk
Requires-Dist: rouge
Requires-Dist: jieba
Requires-Dist: rouge_score
Requires-Dist: fuzzywuzzy
Requires-Dist: html2text
Requires-Dist: bs4
Requires-Dist: seaborn
Requires-Dist: json_repair
Requires-Dist: wonderwords
Requires-Dist: tenacity
Requires-Dist: scipy
Requires-Dist: datasets
Requires-Dist: fraction
Requires-Dist: pymorphy2
Requires-Dist: evaluate
Requires-Dist: rwkv
Requires-Dist: jsonlines
Dynamic: license-file
